numworks_env/__init__.py
numworks_env/cmath.py
numworks_env/ion.py
numworks_env/kandinsky.py
numworks_env/math.py
numworks_env/matplotlib/__init__.py
numworks_env/matplotlib/pyplot.py
numworks_env/numpy.py
numworks_env/random.py
numworks_env/time.py
numworks_env/turtle.py
numworks_env-0.1.1.dist-info/METADATA
numworks_env-0.1.1.dist-info/WHEEL
numworks_env-0.1.1.dist-info/RECORD
